setup.py
salure_helpers/leapsome/__init__.py
salure_helpers/leapsome/api_interface.py
salure_helpers/leapsome/sftp_interface.py
salure_helpers_leapsome.egg-info/PKG-INFO
salure_helpers_leapsome.egg-info/SOURCES.txt
salure_helpers_leapsome.egg-info/dependency_links.txt
salure_helpers_leapsome.egg-info/not-zip-safe
salure_helpers_leapsome.egg-info/requires.txt
salure_helpers_leapsome.egg-info/top_level.txt