Metadata-Version: 1.0
Name: salure-helpers-leapsome
Version: 1.2.0
Summary: Leapsome wrapper from Salure
Home-page: UNKNOWN
Author: D&A Salure
Author-email: support@salureconnnect.com
License: Salure License
Platform: UNKNOWN
